remixer_pytorch/__init__.py
remixer_pytorch/remixer_pytorch.py
remixer_pytorch-0.0.3.dist-info/LICENSE
remixer_pytorch-0.0.3.dist-info/METADATA
remixer_pytorch-0.0.3.dist-info/WHEEL
remixer_pytorch-0.0.3.dist-info/top_level.txt
remixer_pytorch-0.0.3.dist-info/RECORD
